nonebot_plugin_manosaba_memes/__init__.py
nonebot_plugin_manosaba_memes/drawer.py
nonebot_plugin_manosaba_memes/models.py
nonebot_plugin_manosaba_memes/utils.py
nonebot_plugin_manosaba_memes/assets/anan/base.png
nonebot_plugin_manosaba_memes/assets/anan/base_overlay.png
nonebot_plugin_manosaba_memes/assets/anan/害羞.png
nonebot_plugin_manosaba_memes/assets/anan/开心.png
nonebot_plugin_manosaba_memes/assets/anan/无语.png
nonebot_plugin_manosaba_memes/assets/anan/生气.png
nonebot_plugin_manosaba_memes/assets/anan/病娇.png
nonebot_plugin_manosaba_memes/assets/fonts/SourceHanSansSC-Bold.otf
nonebot_plugin_manosaba_memes/assets/fonts/SourceHanSerifSC.otf
nonebot_plugin_manosaba_memes/assets/trial/agreement.png
nonebot_plugin_manosaba_memes/assets/trial/background.png
nonebot_plugin_manosaba_memes/assets/trial/black.png
nonebot_plugin_manosaba_memes/assets/trial/doubt.png
nonebot_plugin_manosaba_memes/assets/trial/ema.png
nonebot_plugin_manosaba_memes/assets/trial/hiro.png
nonebot_plugin_manosaba_memes/assets/trial/option.png
nonebot_plugin_manosaba_memes/assets/trial/perjury.png
nonebot_plugin_manosaba_memes/assets/trial/refutation.png
nonebot_plugin_manosaba_memes-0.1.3.dist-info/licenses/LICENSE
nonebot_plugin_manosaba_memes-0.1.3.dist-info/METADATA
nonebot_plugin_manosaba_memes-0.1.3.dist-info/WHEEL
nonebot_plugin_manosaba_memes-0.1.3.dist-info/top_level.txt
nonebot_plugin_manosaba_memes-0.1.3.dist-info/RECORD
