Metadata-Version: 2.4
Name: nonebot-plugin-manosaba-memes
Version: 0.1.3
Summary: A NoneBot2 plugin for drawing Manosaba memes
Requires-Python: >=3.10
License-File: LICENSE
Requires-Dist: nonebot-plugin-alconna>=0.60.3
Requires-Dist: nonebot2>=2.4.4
Requires-Dist: sketchbook-py>=0.2.1
Dynamic: license-file
